odoo/addons/ssi_l10n_id_taxform_pph_21/README.rst
odoo/addons/ssi_l10n_id_taxform_pph_21/__init__.py
odoo/addons/ssi_l10n_id_taxform_pph_21/__manifest__.py
odoo/addons/ssi_l10n_id_taxform_pph_21/menu.xml
odoo/addons/ssi_l10n_id_taxform_pph_21/data/ptkp_category_data.xml
odoo/addons/ssi_l10n_id_taxform_pph_21/demo/pph_21_biaya_jabatan_demo.xml
odoo/addons/ssi_l10n_id_taxform_pph_21/demo/pph_21_npwp_rate_modifier_demo.xml
odoo/addons/ssi_l10n_id_taxform_pph_21/demo/pph_21_rate_demo.xml
odoo/addons/ssi_l10n_id_taxform_pph_21/demo/ptkp_demo.xml
odoo/addons/ssi_l10n_id_taxform_pph_21/models/__init__.py
odoo/addons/ssi_l10n_id_taxform_pph_21/models/pph_21_biaya_jabatan.py
odoo/addons/ssi_l10n_id_taxform_pph_21/models/pph_21_npwp_rate_modifier.py
odoo/addons/ssi_l10n_id_taxform_pph_21/models/pph_21_rate.py
odoo/addons/ssi_l10n_id_taxform_pph_21/models/pph_21_rate_line.py
odoo/addons/ssi_l10n_id_taxform_pph_21/models/pph_21_ter.py
odoo/addons/ssi_l10n_id_taxform_pph_21/models/pph_21_ter_line.py
odoo/addons/ssi_l10n_id_taxform_pph_21/models/pph_21_ter_line_categ.py
odoo/addons/ssi_l10n_id_taxform_pph_21/models/ptkp.py
odoo/addons/ssi_l10n_id_taxform_pph_21/models/ptkp_category.py
odoo/addons/ssi_l10n_id_taxform_pph_21/models/ptkp_line.py
odoo/addons/ssi_l10n_id_taxform_pph_21/models/res_partner.py
odoo/addons/ssi_l10n_id_taxform_pph_21/security/ir.model.access.csv
odoo/addons/ssi_l10n_id_taxform_pph_21/security/res_group_data.xml
odoo/addons/ssi_l10n_id_taxform_pph_21/static/description/icon.png
odoo/addons/ssi_l10n_id_taxform_pph_21/views/pph_21_biaya_jabatan_views.xml
odoo/addons/ssi_l10n_id_taxform_pph_21/views/pph_21_npwp_rate_modifier_views.xml
odoo/addons/ssi_l10n_id_taxform_pph_21/views/pph_21_rate_views.xml
odoo/addons/ssi_l10n_id_taxform_pph_21/views/pph_21_ter_line_views.xml
odoo/addons/ssi_l10n_id_taxform_pph_21/views/pph_21_ter_views.xml
odoo/addons/ssi_l10n_id_taxform_pph_21/views/ptkp_category_views.xml
odoo14_addon_ssi_l10n_id_taxform_pph_21-14.0.2.0.0.dist-info/METADATA
odoo14_addon_ssi_l10n_id_taxform_pph_21-14.0.2.0.0.dist-info/WHEEL
odoo14_addon_ssi_l10n_id_taxform_pph_21-14.0.2.0.0.dist-info/top_level.txt
odoo14_addon_ssi_l10n_id_taxform_pph_21-14.0.2.0.0.dist-info/RECORD
