Metadata-Version: 2.1
Name: odoo14-addon-ssi-l10n-id-taxform-pph-21
Version: 14.0.2.0.0
Summary: Indonesia's PPh 21 Taxform
Home-page: https://simetri-sinergi.id
Author: PT. Simetri Sinergi Indonesia, OpenSynergy Indonesia
License: AGPL-3
Platform: UNKNOWN
Classifier: Programming Language :: Python
Classifier: Framework :: Odoo
Classifier: Framework :: Odoo :: 14.0
Classifier: License :: OSI Approved :: GNU Affero General Public License v3
Requires-Python: >=3.6
Requires-Dist: odoo14-addon-ssi-l10n-id-taxform
Requires-Dist: odoo <14.1dev,>=14.0a
